Metadata-Version: 2.1
Name: CRRD
Version: 0.1.0
Summary: China Railway Radio Decoder
Home-page: https://github.com/radonyl/CRRD
Author: radonyl
Author-email: alex.l.manstein@gmail.com
License: MIT
Keywords: railway radio decoder
Platform: any
Classifier: Programming Language :: Python :: 3
Classifier: License :: OSI Approved :: MIT License
Classifier: Operating System :: OS Independent
Requires-Python: >=3.7, <4
